Metadata-Version: 2.1
Name: waggon
Version: 0.6.1
Summary: WAsserstein Global Gradient-free OptimisatioN (WAGGON) methods library.
Home-page: https://github.com/hse-cs/waggon
Author: Tigran Ramazyan
Author-email: ramazyant@gmail.com
License: MIT
Classifier: License :: OSI Approved :: MIT License
Classifier: Programming Language :: Python :: 3.11
Classifier: Operating System :: OS Independent
Requires-Python: >=3.11
License-File: LICENSE.txt
Requires-Dist: GPy==1.13.2
Requires-Dist: gpytorch==1.10.0
Requires-Dist: matplotlib==3.7.5
Requires-Dist: numpy>=1.26.2
Requires-Dist: scikit-learn==1.3.2
Requires-Dist: scipy==1.12.0
Requires-Dist: setuptools==72.1.0
Requires-Dist: torch==2.2.2
Requires-Dist: torchbnn==1.2
Requires-Dist: torchensemble==0.1.9
Requires-Dist: tqdm==4.66.4
Provides-Extra: dev
Requires-Dist: pytest>=7.0; extra == "dev"
Requires-Dist: twine>=4.0.2; extra == "dev"
